lammps_simulator/__init__.py
lammps_simulator/computer.py
lammps_simulator/device.py
lammps_simulator/simulator.py
lammps_simulator-1.1.1.dist-info/LICENSE
lammps_simulator-1.1.1.dist-info/METADATA
lammps_simulator-1.1.1.dist-info/WHEEL
lammps_simulator-1.1.1.dist-info/top_level.txt
lammps_simulator-1.1.1.dist-info/RECORD
