Metadata-Version: 2.1
Name: lammps-simulator
Version: 1.1.1
Summary: Python interface for running LAMMPS input scripts
Home-page: http://github.com/evenmn/lammps-simulator
Author: Even Marius Nordhagen
Author-email: evenmn@mn.uio.no
License: MIT
Platform: UNKNOWN
License-File: LICENSE
